{"is_source_file": false, "format": "", "description": "", "external_files": [], "external_methods": [], "published": [], "classes": [], "methods": [], "calls": [], "search-terms": ["app-header", "app-sidebar", "app-note-list", "app-note-editor", "create", "searchChange", "onCreate", "onSearch", "onLogout", "loading", "filteredNotes", "onSelect", "onDelete", "onCancelEditor", "onSaveEditor", "editorOpen", "editingNote"], "state": 2, "file_id": 46, "knowledge_revision": 94, "git_revision": "", "hash": "a98db0ea634cd51095b206937441bb17", "format-version": 4, "code-base-name": "notes_frontend", "filename": "notes_frontend/src/app/pages/home/home.component.html", "revision_history": [{"94": ""}]}